file_conversor/AUTHORS.md
file_conversor/LICENSE
file_conversor/README.md
file_conversor/__init__.py
file_conversor/__main__.py
file_conversor/pyproject.toml
file_conversor/.icons/180_degrees.ico
file_conversor/.icons/30.ico
file_conversor/.icons/60.ico
file_conversor/.icons/avi.ico
file_conversor/.icons/azw3.ico
file_conversor/.icons/blur.ico
file_conversor/.icons/brightness.ico
file_conversor/.icons/check.ico
file_conversor/.icons/color.ico
file_conversor/.icons/compress.ico
file_conversor/.icons/config.ico
file_conversor/.icons/contrast.ico
file_conversor/.icons/convert.ico
file_conversor/.icons/csv.ico
file_conversor/.icons/diagonal_line.ico
file_conversor/.icons/doc.ico
file_conversor/.icons/docx.ico
file_conversor/.icons/epub.ico
file_conversor/.icons/extract.ico
file_conversor/.icons/fb2.ico
file_conversor/.icons/filter.ico
file_conversor/.icons/gamma.ico
file_conversor/.icons/html.ico
file_conversor/.icons/icon.ico
file_conversor/.icons/icon.png
file_conversor/.icons/info.ico
file_conversor/.icons/ini.ico
file_conversor/.icons/jpg.ico
file_conversor/.icons/json.ico
file_conversor/.icons/left_right.ico
file_conversor/.icons/m4a.ico
file_conversor/.icons/merge.ico
file_conversor/.icons/mkv.ico
file_conversor/.icons/mobi.ico
file_conversor/.icons/mp3.ico
file_conversor/.icons/mp4.ico
file_conversor/.icons/new_file.ico
file_conversor/.icons/ocr.ico
file_conversor/.icons/odp.ico
file_conversor/.icons/ods.ico
file_conversor/.icons/odt.ico
file_conversor/.icons/padlock_locked.ico
file_conversor/.icons/padlock_unlocked.ico
file_conversor/.icons/pdf.ico
file_conversor/.icons/pipeline.ico
file_conversor/.icons/png.ico
file_conversor/.icons/ppt.ico
file_conversor/.icons/pptx.ico
file_conversor/.icons/pwr_btn.ico
file_conversor/.icons/repair.ico
file_conversor/.icons/resize.ico
file_conversor/.icons/rotate_left.ico
file_conversor/.icons/rotate_right.ico
file_conversor/.icons/run.ico
file_conversor/.icons/separate.ico
file_conversor/.icons/sha256.ico
file_conversor-0.7.4.dist-info/licenses/AUTHORS.md
file_conversor-0.7.4.dist-info/licenses/LICENSE
file_conversor-0.7.4.dist-info/licenses/README.md
file_conversor-0.7.4.dist-info/METADATA
file_conversor-0.7.4.dist-info/WHEEL
file_conversor-0.7.4.dist-info/entry_points.txt
file_conversor-0.7.4.dist-info/top_level.txt
file_conversor-0.7.4.dist-info/RECORD
