Metadata-Version: 2.4
Name: file_conversor
Version: 0.7.4
Summary: Universal file conversor for multimedia files (audio, video, pdf, docs, etc)
Author-email: Andre Luiz Romano Madureira <andre@domain.com>
Project-URL: Homepage, https://github.com/andre-romano/file_conversor
Keywords: file,conversion,multimedia,docs,video,audio,image,converter
Classifier: Programming Language :: Python :: 3
Classifier: Programming Language :: Python :: 3.13
Classifier: Operating System :: OS Independent
Requires-Python: <=3.13.7,>=3.12
License-File: LICENSE
License-File: AUTHORS.md
License-File: README.md
Requires-Dist: typer>=0.16.0
Requires-Dist: rich>=14.0.0
Requires-Dist: Babel>=2.17.0
Requires-Dist: pypdf>=5.8.0
Requires-Dist: cryptography>=45.0.5
Requires-Dist: pillow>=11.3.0
Requires-Dist: img2pdf>=0.6.1
Requires-Dist: pywin32>=311; sys_platform == "win32"
Requires-Dist: pymupdf>=1.26.3
Requires-Dist: pyyaml>=6.0.2
Requires-Dist: xmltodict>=0.14.2
Requires-Dist: toml>=0.10.2
Requires-Dist: concurrent-log-handler>=0.9.28
Requires-Dist: portalocker>=3.2.0
Requires-Dist: ocrmypdf>=16.11.0
Requires-Dist: requests>=2.32.5
Requires-Dist: flask>=3.1.2
Requires-Dist: dominate>=2.9.1
Requires-Dist: pywebview>=6.1
Requires-Dist: pycountry>=24.6.1
Requires-Dist: platformdirs>=4.5.0
Requires-Dist: natsort>=8.4.0
Requires-Dist: pdf2docx>=0.5.8
Requires-Dist: requests-cache>=1.2.1
Dynamic: license-file
